exasol/pytest_extension/__init__.py
exasol/pytest_extension/py.typed
exasol/pytest_extension/version.py
pytest_exasol_extension-0.2.5.dist-info/METADATA
pytest_exasol_extension-0.2.5.dist-info/WHEEL
pytest_exasol_extension-0.2.5.dist-info/entry_points.txt
pytest_exasol_extension-0.2.5.dist-info/RECORD
