Metadata-Version: 2.3
Name: pytest-exasol-extension
Version: 0.2.5
Summary: 
Author: Mikhail Beck
Author-email: mikhail.beck@exasol.com
Requires-Python: >=3.10,<3.14
Classifier: Programming Language :: Python :: 3
Classifier: Programming Language :: Python :: 3.10
Classifier: Programming Language :: Python :: 3.11
Classifier: Programming Language :: Python :: 3.12
Classifier: Programming Language :: Python :: 3.13
Requires-Dist: exasol-python-extension-common (>=0.10.0,<1)
Requires-Dist: exasol-saas-api (>=2.3,<3)
Requires-Dist: pyexasol (>1,<2)
Requires-Dist: pytest (>=7,<9)
Requires-Dist: pytest-exasol-backend (>=1.1,<2)
